{"result":[{"loc_oid":1,"uv":0,"temp":3.111,"yearlyrainin":41.148,"dewpoint":2.239,"feelslike":3.111,"winddir":213,"hourlyrainin":0.0,"TIME":"2021-02-22 00:08:00","monthlyrainin":26.162,"dailyrainin":0.0,"solarradiation":0.0,"windgust":0.0,"humidity":94.0,"windspeed":0.0,"id":3519,"maxdailygust":0.0,"weeklyrainin":0.0},{"loc_oid":1,"uv":0,"temp":2.889,"yearlyrainin":41.148,"dewpoint":2.167,"feelslike":2.889,"winddir":10,"hourlyrainin":0.0,"TIME":"2021-02-22 00:18:00","monthlyrainin":26.162,"dailyrainin":0.0,"solarradiation":0.0,"windgust":1.118,"humidity":95.0,"windspeed":0.179,"id":3520,"maxdailygust":2.19,"weeklyrainin":0.0},{"loc_oid":1,"uv":0,"temp":3.0,"yearlyrainin":41.148,"dewpoint":1.978,"feelslike":3.0,"winddir":173,"hourlyrainin":0.0,"TIME":"2021-02-22 00:28:00","monthlyrainin":26.162,"dailyrainin":0.0,"solarradiation":0.0,"windgust":0.0,"humidity":93.0,"windspeed":0.0,"id":3521,"maxdailygust":2.19,"weeklyrainin":0.0},{"loc_oid":1,"uv":0,"temp":3.0,"yearlyrainin":41.148,"dewpoint":1.978,"feelslike":3.0,"winddir":109,"hourlyrainin":0.0,"TIME":"2021-02-22 00:38:00","monthlyrainin":26.162,"dailyrainin":0.0,"solarradiation":0.0,"windgust":0.0,"humidity":93.0,"windspeed":0.0,"id":3522,"maxdailygust":2.19,"weeklyrainin":0.0},{"loc_oid":1,"uv":0,"temp":2.889,"yearlyrainin":41.148,"dewpoint":2.022,"feelslike":2.889,"winddir":180,"hourlyrainin":0.0,"TIME":"2021-02-22 00:48:00","monthlyrainin":26.162,"dailyrainin":0.0,"solarradiation":0.0,"windgust":0.0,"humidity":94.0,"windspeed":0.0,"id":3523,"maxdailygust":2.19,"weeklyrainin":0.0},{"loc_oid":1,"uv":0,"temp":2.778,"yearlyrainin":41.148,"dewpoint":2.056,"feelslike":2.778,"winddir":169,"hourlyrainin":0.0,"TIME":"2021-02-22 00:58:00","monthlyrainin":26.162,"dailyrainin":0.0,"solarradiation":0.0,"windgust":0.0,"humidity":95.0,"windspeed":0.0,"id":3524,"maxdailygust":2.19,"weeklyrainin":0.0},{"loc_oid":1,"uv":0,"temp":2.5,"yearlyrainin":41.148,"dewpoint":1.783,"feelslike":2.5,"winddir":169,"hourlyrainin":0.0,"TIME":"2021-02-22 01:08:00","monthlyrainin":26.162,"dailyrainin":0.0,"solarradiation":0.0,"windgust":0.0,"humidity":95.0,"windspeed":0.0,"id":3525,"maxdailygust":2.19,"weeklyrainin":0.0},{"loc_oid":1,"uv":0,"temp":2.278,"yearlyrainin":41.148,"dewpoint":1.561,"feelslike":2.278,"winddir":329,"hourlyrainin":0.0,"TIME":"2021-02-22 01:18:00","monthlyrainin":26.162,"dailyrainin":0.0,"solarradiation":0.0,"windgust":1.118,"humidity":95.0,"windspeed":0.0,"id":3526,"maxdailygust":2.19,"weeklyrainin":0.0},{"loc_oid":1,"uv":0,"temp":2.111,"yearlyrainin":41.148,"dewpoint":1.394,"feelslike":2.111,"winddir":78,"hourlyrainin":0.0,"TIME":"2021-02-22 01:28:00","monthlyrainin":26.162,"dailyrainin":0.0,"solarradiation":0.0,"windgust":0.0,"humidity":95.0,"windspeed":0.0,"id":3527,"maxdailygust":2.19,"weeklyrainin":0.0},{"loc_oid":1,"uv":0,"temp":2.0,"yearlyrainin":41.148,"dewpoint":1.428,"feelslike":2.0,"winddir":113,"hourlyrainin":0.0,"TIME":"2021-02-22 01:38:00","monthlyrainin":26.162,"dailyrainin":0.0,"solarradiation":0.0,"windgust":0.0,"humidity":96.0,"windspeed":0.0,"id":3528,"maxdailygust":2.19,"weeklyrainin":0.0},{"loc_oid":1,"uv":0,"temp":1.889,"yearlyrainin":41.148,"dewpoint":1.317,"feelslike":1.889,"winddir":111,"hourlyrainin":0.0,"TIME":"2021-02-22 01:48:00","monthlyrainin":26.162,"dailyrainin":0.0,"solarradiation":0.0,"windgust":0.0,"humidity":96.0,"windspeed":0.0,"id":3529,"maxdailygust":2.19,"weeklyrainin":0.0},{"loc_oid":1,"uv":0,"temp":1.778,"yearlyrainin":41.148,"dewpoint":1.061,"feelslike":1.778,"winddir":115,"hourlyrainin":0.0,"TIME":"2021-02-22 01:58:00","monthlyrainin":26.162,"dailyrainin":0.0,"solarradiation":0.0,"windgust":0.0,"humidity":95.0,"windspeed":0.0,"id":3530,"maxdailygust":2.19,"weeklyrainin":0.0},{"loc_oid":1,"uv":0,"temp":1.611,"yearlyrainin":41.148,"dewpoint":1.044,"feelslike":1.611,"winddir":105,"hourlyrainin":0.0,"TIME":"2021-02-22 02:08:00","monthlyrainin":26.162,"dailyrainin":0.0,"solarradiation":0.0,"windgust":0.0,"humidity":96.0,"windspeed":0.0,"id":3531,"maxdailygust":2.19,"weeklyrainin":0.0},{"loc_oid":1,"uv":0,"temp":1.611,"yearlyrainin":41.148,"dewpoint":1.044,"feelslike":1.611,"winddir":85,"hourlyrainin":0.0,"TIME":"2021-02-22 02:18:00","monthlyrainin":26.162,"dailyrainin":0.0,"solarradiation":0.0,"windgust":0.0,"humidity":96.0,"windspeed":0.0,"id":3532,"maxdailygust":2.19,"weeklyrainin":0.0},{"loc_oid":1,"uv":0,"temp":1.389,"yearlyrainin":41.148,"dewpoint":0.822,"feelslike":1.389,"winddir":174,"hourlyrainin":0.0,"TIME":"2021-02-22 02:28:00","monthlyrainin":26.162,"dailyrainin":0.0,"solarradiation":0.0,"windgust":0.0,"humidity":96.0,"windspeed":0.0,"id":3533,"maxdailygust":2.19,"weeklyrainin":0.0},{"loc_oid":1,"uv":0,"temp":1.278,"yearlyrainin":41.148,"dewpoint":0.711,"feelslike":1.278,"winddir":151,"hourlyrainin":0.0,"TIME":"2021-02-22 02:38:00","monthlyrainin":26.162,"dailyrainin":0.0,"solarradiation":0.0,"windgust":0.0,"humidity":96.0,"windspeed":0.0,"id":3534,"maxdailygust":2.19,"weeklyrainin":0.0},{"loc_oid":1,"uv":0,"temp":1.222,"yearlyrainin":41.148,"dewpoint":0.656,"feelslike":1.222,"winddir":238,"hourlyrainin":0.0,"TIME":"2021-02-22 02:48:00","monthlyrainin":26.162,"dailyrainin":0.0,"solarradiation":0.0,"windgust":0.0,"humidity":96.0,"windspeed":0.0,"id":3535,"maxdailygust":2.19,"weeklyrainin":0.0},{"loc_oid":1,"uv":0,"temp":1.111,"yearlyrainin":41.148,"dewpoint":0.544,"feelslike":1.111,"winddir":113,"hourlyrainin":0.0,"TIME":"2021-02-22 02:58:00","monthlyrainin":26.162,"dailyrainin":0.0,"solarradiation":0.0,"windgust":0.0,"humidity":96.0,"windspeed":0.0,"id":3536,"maxdailygust":2.19,"weeklyrainin":0.0},{"loc_oid":1,"uv":0,"temp":0.889,"yearlyrainin":41.148,"dewpoint":0.322,"feelslike":0.889,"winddir":187,"hourlyrainin":0.0,"TIME":"2021-02-22 03:08:00","monthlyrainin":26.162,"dailyrainin":0.0,"solarradiation":0.0,"windgust":0.0,"humidity":96.0,"windspeed":0.0,"id":3537,"maxdailygust":2.19,"weeklyrainin":0.0},{"loc_oid":1,"uv":0,"temp":0.778,"yearlyrainin":41.148,"dewpoint":0.211,"feelslike":0.778,"winddir":183,"hourlyrainin":0.0,"TIME":"2021-02-22 03:18:00","monthlyrainin":26.162,"dailyrainin":0.0,"solarradiation":0.0,"windgust":0.0,"humidity":96.0,"windspeed":0.0,"id":3538,"maxdailygust":2.19,"weeklyrainin":0.0},{"loc_oid":1,"uv":0,"temp":0.778,"yearlyrainin":41.148,"dewpoint":0.211,"feelslike":0.778,"winddir":190,"hourlyrainin":0.0,"TIME":"2021-02-22 03:28:00","monthlyrainin":26.162,"dailyrainin":0.0,"solarradiation":0.0,"windgust":0.0,"humidity":96.0,"windspeed":0.0,"id":3539,"maxdailygust":2.19,"weeklyrainin":0.0},{"loc_oid":1,"uv":0,"temp":0.722,"yearlyrainin":41.148,"dewpoint":0.156,"feelslike":0.722,"winddir":119,"hourlyrainin":0.0,"TIME":"2021-02-22 03:38:00","monthlyrainin":26.162,"dailyrainin":0.0,"solarradiation":0.0,"windgust":0.0,"humidity":96.0,"windspeed":0.0,"id":3540,"maxdailygust":2.19,"weeklyrainin":0.0},{"loc_oid":1,"uv":0,"temp":0.611,"yearlyrainin":41.148,"dewpoint":0.05,"feelslike":0.611,"winddir":159,"hourlyrainin":0.0,"TIME":"2021-02-22 03:48:00","monthlyrainin":26.162,"dailyrainin":0.0,"solarradiation":0.0,"windgust":0.0,"humidity":96.0,"windspeed":0.0,"id":3541,"maxdailygust":2.19,"weeklyrainin":0.0},{"loc_oid":1,"uv":0,"temp":0.611,"yearlyrainin":41.148,"dewpoint":0.05,"feelslike":0.611,"winddir":226,"hourlyrainin":0.0,"TIME":"2021-02-22 03:58:00","monthlyrainin":26.162,"dailyrainin":0.0,"solarradiation":0.0,"windgust":0.0,"humidity":96.0,"windspeed":0.0,"id":3542,"maxdailygust":2.19,"weeklyrainin":0.0},{"loc_oid":1,"uv":0,"temp":0.389,"yearlyrainin":41.148,"dewpoint":-0.033,"feelslike":0.389,"winddir":88,"hourlyrainin":0.0,"TIME":"2021-02-22 04:08:00","monthlyrainin":26.162,"dailyrainin":0.0,"solarradiation":0.0,"windgust":0.0,"humidity":97.0,"windspeed":0.0,"id":3543,"maxdailygust":2.19,"weeklyrainin":0.0},{"loc_oid":1,"uv":0,"temp":0.389,"yearlyrainin":41.148,"dewpoint":-0.172,"feelslike":0.389,"winddir":92,"hourlyrainin":0.0,"TIME":"2021-02-22 04:18:00","monthlyrainin":26.162,"dailyrainin":0.0,"solarradiation":0.0,"windgust":0.0,"humidity":96.0,"windspeed":0.0,"id":3544,"maxdailygust":2.19,"weeklyrainin":0.0},{"loc_oid":1,"uv":0,"temp":0.278,"yearlyrainin":41.148,"dewpoint":-0.144,"feelslike":0.278,"winddir":103,"hourlyrainin":0.0,"TIME":"2021-02-22 04:28:00","monthlyrainin":26.162,"dailyrainin":0.0,"solarradiation":0.0,"windgust":0.0,"humidity":97.0,"windspeed":0.0,"id":3545,"maxdailygust":2.19,"weeklyrainin":0.0},{"loc_oid":1,"uv":0,"temp":0.222,"yearlyrainin":41.148,"dewpoint":-0.194,"feelslike":0.222,"winddir":102,"hourlyrainin":0.0,"TIME":"2021-02-22 04:38:00","monthlyrainin":26.162,"dailyrainin":0.0,"solarradiation":0.0,"windgust":0.0,"humidity":97.0,"windspeed":0.0,"id":3546,"maxdailygust":2.19,"weeklyrainin":0.0},{"loc_oid":1,"uv":0,"temp":0.222,"yearlyrainin":41.148,"dewpoint":-0.194,"feelslike":0.222,"winddir":100,"hourlyrainin":0.0,"TIME":"2021-02-22 04:48:00","monthlyrainin":26.162,"dailyrainin":0.0,"solarradiation":0.0,"windgust":0.0,"humidity":97.0,"windspeed":0.0,"id":3547,"maxdailygust":2.19,"weeklyrainin":0.0},{"loc_oid":1,"uv":0,"temp":0.222,"yearlyrainin":41.148,"dewpoint":-0.194,"feelslike":0.222,"winddir":92,"hourlyrainin":0.0,"TIME":"2021-02-22 04:58:00","monthlyrainin":26.162,"dailyrainin":0.0,"solarradiation":0.0,"windgust":0.0,"humidity":97.0,"windspeed":0.0,"id":3548,"maxdailygust":2.19,"weeklyrainin":0.0},{"loc_oid":1,"uv":0,"temp":0.111,"yearlyrainin":41.148,"dewpoint":-0.306,"feelslike":0.111,"winddir":94,"hourlyrainin":0.0,"TIME":"2021-02-22 05:08:00","monthlyrainin":26.162,"dailyrainin":0.0,"solarradiation":0.0,"windgust":0.0,"humidity":97.0,"windspeed":0.0,"id":3549,"maxdailygust":2.19,"weeklyrainin":0.0},{"loc_oid":1,"uv":0,"temp":0.111,"yearlyrainin":41.148,"dewpoint":-0.306,"feelslike":0.111,"winddir":95,"hourlyrainin":0.0,"TIME":"2021-02-22 05:18:00","monthlyrainin":26.162,"dailyrainin":0.0,"solarradiation":0.0,"windgust":0.0,"humidity":97.0,"windspeed":0.0,"id":3550,"maxdailygust":2.19,"weeklyrainin":0.0},{"loc_oid":1,"uv":0,"temp":0.0,"yearlyrainin":41.148,"dewpoint":-0.417,"feelslike":0.0,"winddir":94,"hourlyrainin":0.0,"TIME":"2021-02-22 05:28:00","monthlyrainin":26.162,"dailyrainin":0.0,"solarradiation":0.0,"windgust":0.0,"humidity":97.0,"windspeed":0.0,"id":3551,"maxdailygust":2.19,"weeklyrainin":0.0},{"loc_oid":1,"uv":0,"temp":0.0,"yearlyrainin":41.148,"dewpoint":-0.417,"feelslike":0.0,"winddir":95,"hourlyrainin":0.0,"TIME":"2021-02-22 05:38:00","monthlyrainin":26.162,"dailyrainin":0.0,"solarradiation":0.0,"windgust":0.0,"humidity":97.0,"windspeed":0.0,"id":3552,"maxdailygust":2.19,"weeklyrainin":0.0},{"loc_oid":1,"uv":0,"temp":0.0,"yearlyrainin":41.148,"dewpoint":-0.417,"feelslike":0.0,"winddir":95,"hourlyrainin":0.0,"TIME":"2021-02-22 05:48:00","monthlyrainin":26.162,"dailyrainin":0.0,"solarradiation":0.0,"windgust":0.0,"humidity":97.0,"windspeed":0.0,"id":3553,"maxdailygust":2.19,"weeklyrainin":0.0},{"loc_oid":1,"uv":0,"temp":0.0,"yearlyrainin":41.148,"dewpoint":-0.417,"feelslike":0.0,"winddir":95,"hourlyrainin":0.0,"TIME":"2021-02-22 05:58:00","monthlyrainin":26.162,"dailyrainin":0.0,"solarradiation":0.0,"windgust":0.0,"humidity":97.0,"windspeed":0.0,"id":3554,"maxdailygust":2.19,"weeklyrainin":0.0},{"loc_oid":1,"uv":0,"temp":0.111,"yearlyrainin":41.148,"dewpoint":-0.306,"feelslike":0.111,"winddir":94,"hourlyrainin":0.0,"TIME":"2021-02-22 06:08:00","monthlyrainin":26.162,"dailyrainin":0.0,"solarradiation":0.0,"windgust":0.0,"humidity":97.0,"windspeed":0.0,"id":3555,"maxdailygust":2.19,"weeklyrainin":0.0},{"loc_oid":1,"uv":0,"temp":0.222,"yearlyrainin":41.148,"dewpoint":-0.194,"feelslike":0.222,"winddir":77,"hourlyrainin":0.0,"TIME":"2021-02-22 06:18:00","monthlyrainin":26.162,"dailyrainin":0.0,"solarradiation":0.0,"windgust":0.0,"humidity":97.0,"windspeed":0.0,"id":3556,"maxdailygust":2.19,"weeklyrainin":0.0},{"loc_oid":1,"uv":0,"temp":0.5,"yearlyrainin":41.148,"dewpoint":0.078,"feelslike":0.5,"winddir":351,"hourlyrainin":0.0,"TIME":"2021-02-22 06:28:00","monthlyrainin":26.162,"dailyrainin":0.0,"solarradiation":0.0,"windgust":0.0,"humidity":97.0,"windspeed":0.0,"id":3557,"maxdailygust":2.19,"weeklyrainin":0.0},{"loc_oid":1,"uv":0,"temp":0.778,"yearlyrainin":41.148,"dewpoint":0.356,"feelslike":0.778,"winddir":353,"hourlyrainin":0.0,"TIME":"2021-02-22 06:38:00","monthlyrainin":26.162,"dailyrainin":0.0,"solarradiation":0.0,"windgust":0.0,"humidity":97.0,"windspeed":0.0,"id":3558,"maxdailygust":2.19,"weeklyrainin":0.0},{"loc_oid":1,"uv":0,"temp":0.889,"yearlyrainin":41.148,"dewpoint":0.467,"feelslike":0.889,"winddir":354,"hourlyrainin":0.0,"TIME":"2021-02-22 06:48:00","monthlyrainin":26.162,"dailyrainin":0.0,"solarradiation":0.0,"windgust":0.0,"humidity":97.0,"windspeed":0.0,"id":3559,"maxdailygust":2.19,"weeklyrainin":0.0},{"loc_oid":1,"uv":0,"temp":1.0,"yearlyrainin":41.148,"dewpoint":0.578,"feelslike":1.0,"winddir":354,"hourlyrainin":0.0,"TIME":"2021-02-22 06:58:00","monthlyrainin":26.162,"dailyrainin":0.0,"solarradiation":0.0,"windgust":0.0,"humidity":97.0,"windspeed":0.0,"id":3560,"maxdailygust":2.19,"weeklyrainin":0.0},{"loc_oid":1,"uv":0,"temp":1.222,"yearlyrainin":41.148,"dewpoint":0.8,"feelslike":1.222,"winddir":353,"hourlyrainin":0.0,"TIME":"2021-02-22 07:08:00","monthlyrainin":26.162,"dailyrainin":0.0,"solarradiation":0.0,"windgust":0.0,"humidity":97.0,"windspeed":0.0,"id":3561,"maxdailygust":2.19,"weeklyrainin":0.0},{"loc_oid":1,"uv":0,"temp":1.278,"yearlyrainin":41.148,"dewpoint":0.856,"feelslike":1.278,"winddir":354,"hourlyrainin":0.0,"TIME":"2021-02-22 07:18:00","monthlyrainin":26.162,"dailyrainin":0.0,"solarradiation":2.14,"windgust":0.0,"humidity":97.0,"windspeed":0.0,"id":3562,"maxdailygust":2.19,"weeklyrainin":0.0},{"loc_oid":1,"uv":0,"temp":1.611,"yearlyrainin":41.148,"dewpoint":1.189,"feelslike":1.611,"winddir":325,"hourlyrainin":0.0,"TIME":"2021-02-22 07:28:00","monthlyrainin":26.162,"dailyrainin":0.0,"solarradiation":8.12,"windgust":0.0,"humidity":97.0,"windspeed":0.0,"id":3563,"maxdailygust":2.19,"weeklyrainin":0.0},{"loc_oid":1,"uv":0,"temp":1.778,"yearlyrainin":41.148,"dewpoint":1.356,"feelslike":1.778,"winddir":324,"hourlyrainin":0.0,"TIME":"2021-02-22 07:38:00","monthlyrainin":26.162,"dailyrainin":0.0,"solarradiation":18.51,"windgust":0.0,"humidity":97.0,"windspeed":0.0,"id":3564,"maxdailygust":2.19,"weeklyrainin":0.0},{"loc_oid":1,"uv":0,"temp":1.889,"yearlyrainin":41.148,"dewpoint":1.461,"feelslike":1.889,"winddir":325,"hourlyrainin":0.0,"TIME":"2021-02-22 07:48:00","monthlyrainin":26.162,"dailyrainin":0.0,"solarradiation":28.16,"windgust":0.0,"humidity":97.0,"windspeed":0.0,"id":3565,"maxdailygust":2.19,"weeklyrainin":0.0},{"loc_oid":1,"uv":1,"temp":2.111,"yearlyrainin":41.148,"dewpoint":1.683,"feelslike":2.111,"winddir":324,"hourlyrainin":0.0,"TIME":"2021-02-22 07:58:00","monthlyrainin":26.162,"dailyrainin":0.0,"solarradiation":41.14,"windgust":0.0,"humidity":97.0,"windspeed":0.0,"id":3566,"maxdailygust":2.19,"weeklyrainin":0.0},{"loc_oid":1,"uv":1,"temp":2.389,"yearlyrainin":41.148,"dewpoint":1.961,"feelslike":2.389,"winddir":344,"hourlyrainin":0.0,"TIME":"2021-02-22 08:08:00","monthlyrainin":26.162,"dailyrainin":0.0,"solarradiation":53.16,"windgust":0.0,"humidity":97.0,"windspeed":0.0,"id":3567,"maxdailygust":2.19,"weeklyrainin":0.0},{"loc_oid":1,"uv":1,"temp":2.611,"yearlyrainin":41.148,"dewpoint":2.183,"feelslike":2.611,"winddir":13,"hourlyrainin":0.0,"TIME":"2021-02-22 08:18:00","monthlyrainin":26.162,"dailyrainin":0.0,"solarradiation":77.51,"windgust":0.0,"humidity":97.0,"windspeed":0.0,"id":3568,"maxdailygust":2.19,"weeklyrainin":0.0},{"loc_oid":1,"uv":1,"temp":2.889,"yearlyrainin":41.148,"dewpoint":2.461,"feelslike":2.889,"winddir":0,"hourlyrainin":0.0,"TIME":"2021-02-22 08:28:00","monthlyrainin":26.162,"dailyrainin":0.0,"solarradiation":93.65,"windgust":0.0,"humidity":97.0,"windspeed":0.0,"id":3569,"maxdailygust":2.19,"weeklyrainin":0.0},{"loc_oid":1,"uv":1,"temp":3.222,"yearlyrainin":41.148,"dewpoint":2.794,"feelslike":3.222,"winddir":325,"hourlyrainin":0.0,"TIME":"2021-02-22 08:38:00","monthlyrainin":26.162,"dailyrainin":0.0,"solarradiation":108.72,"windgust":0.0,"humidity":97.0,"windspeed":0.0,"id":3570,"maxdailygust":2.19,"weeklyrainin":0.0},{"loc_oid":1,"uv":1,"temp":3.611,"yearlyrainin":41.148,"dewpoint":3.178,"feelslike":3.611,"winddir":264,"hourlyrainin":0.0,"TIME":"2021-02-22 08:48:00","monthlyrainin":26.162,"dailyrainin":0.0,"solarradiation":114.73,"windgust":0.0,"humidity":97.0,"windspeed":0.0,"id":3571,"maxdailygust":2.19,"weeklyrainin":0.0},{"loc_oid":1,"uv":1,"temp":4.111,"yearlyrainin":41.148,"dewpoint":3.678,"feelslike":4.111,"winddir":320,"hourlyrainin":0.0,"TIME":"2021-02-22 08:58:00","monthlyrainin":26.162,"dailyrainin":0.0,"solarradiation":127.37,"windgust":0.0,"humidity":97.0,"windspeed":0.0,"id":3572,"maxdailygust":2.19,"weeklyrainin":0.0},{"loc_oid":1,"uv":1,"temp":4.611,"yearlyrainin":41.148,"dewpoint":4.178,"feelslike":4.611,"winddir":319,"hourlyrainin":0.0,"TIME":"2021-02-22 09:08:00","monthlyrainin":26.162,"dailyrainin":0.0,"solarradiation":144.07,"windgust":0.0,"humidity":97.0,"windspeed":0.0,"id":3573,"maxdailygust":2.19,"weeklyrainin":0.0},{"loc_oid":1,"uv":1,"temp":5.111,"yearlyrainin":41.148,"dewpoint":4.672,"feelslike":5.111,"winddir":323,"hourlyrainin":0.0,"TIME":"2021-02-22 09:18:00","monthlyrainin":26.162,"dailyrainin":0.0,"solarradiation":160.91,"windgust":0.0,"humidity":97.0,"windspeed":0.0,"id":3574,"maxdailygust":2.19,"weeklyrainin":0.0},{"loc_oid":1,"uv":2,"temp":5.5,"yearlyrainin":41.148,"dewpoint":5.061,"feelslike":5.5,"winddir":331,"hourlyrainin":0.0,"TIME":"2021-02-22 09:28:00","monthlyrainin":26.162,"dailyrainin":0.0,"solarradiation":184.18,"windgust":0.0,"humidity":97.0,"windspeed":0.0,"id":3575,"maxdailygust":2.19,"weeklyrainin":0.0},{"loc_oid":1,"uv":2,"temp":5.889,"yearlyrainin":41.148,"dewpoint":5.45,"feelslike":5.889,"winddir":49,"hourlyrainin":0.0,"TIME":"2021-02-22 09:38:00","monthlyrainin":26.162,"dailyrainin":0.0,"solarradiation":173.21,"windgust":0.0,"humidity":97.0,"windspeed":0.0,"id":3576,"maxdailygust":2.19,"weeklyrainin":0.0},{"loc_oid":1,"uv":2,"temp":6.222,"yearlyrainin":41.148,"dewpoint":5.783,"feelslike":6.222,"winddir":318,"hourlyrainin":0.0,"TIME":"2021-02-22 09:48:00","monthlyrainin":26.162,"dailyrainin":0.0,"solarradiation":191.34,"windgust":0.0,"humidity":97.0,"windspeed":0.0,"id":3577,"maxdailygust":2.19,"weeklyrainin":0.0},{"loc_oid":1,"uv":2,"temp":6.778,"yearlyrainin":41.148,"dewpoint":6.333,"feelslike":6.778,"winddir":320,"hourlyrainin":0.0,"TIME":"2021-02-22 09:58:00","monthlyrainin":26.162,"dailyrainin":0.0,"solarradiation":224.43,"windgust":0.0,"humidity":97.0,"windspeed":0.0,"id":3578,"maxdailygust":2.19,"weeklyrainin":0.0},{"loc_oid":1,"uv":2,"temp":7.611,"yearlyrainin":41.148,"dewpoint":6.861,"feelslike":7.611,"winddir":342,"hourlyrainin":0.0,"TIME":"2021-02-22 10:08:00","monthlyrainin":26.162,"dailyrainin":0.0,"solarradiation":243.74,"windgust":0.0,"humidity":95.0,"windspeed":0.0,"id":3579,"maxdailygust":2.19,"weeklyrainin":0.0},{"loc_oid":1,"uv":2,"temp":8.389,"yearlyrainin":41.148,"dewpoint":7.167,"feelslike":8.389,"winddir":245,"hourlyrainin":0.0,"TIME":"2021-02-22 10:18:00","monthlyrainin":26.162,"dailyrainin":0.0,"solarradiation":214.36,"windgust":0.0,"humidity":92.0,"windspeed":0.0,"id":3580,"maxdailygust":2.19,"weeklyrainin":0.0},{"loc_oid":1,"uv":2,"temp":9.278,"yearlyrainin":41.148,"dewpoint":7.056,"feelslike":9.278,"winddir":339,"hourlyrainin":0.0,"TIME":"2021-02-22 10:28:00","monthlyrainin":26.162,"dailyrainin":0.0,"solarradiation":224.36,"windgust":0.0,"humidity":86.0,"windspeed":0.0,"id":3581,"maxdailygust":2.19,"weeklyrainin":0.0},{"loc_oid":1,"uv":3,"temp":10.278,"yearlyrainin":41.148,"dewpoint":7.339,"feelslike":10.278,"winddir":330,"hourlyrainin":0.0,"TIME":"2021-02-22 10:38:00","monthlyrainin":26.162,"dailyrainin":0.0,"solarradiation":240.06,"windgust":0.0,"humidity":82.0,"windspeed":0.0,"id":3582,"maxdailygust":2.19,"weeklyrainin":0.0},{"loc_oid":1,"uv":3,"temp":11.611,"yearlyrainin":41.148,"dewpoint":7.522,"feelslike":11.611,"winddir":347,"hourlyrainin":0.0,"TIME":"2021-02-22 10:48:00","monthlyrainin":26.162,"dailyrainin":0.0,"solarradiation":259.12,"windgust":0.0,"humidity":76.0,"windspeed":0.0,"id":3583,"maxdailygust":2.19,"weeklyrainin":0.0},{"loc_oid":1,"uv":3,"temp":13.111,"yearlyrainin":41.148,"dewpoint":8.378,"feelslike":13.111,"winddir":309,"hourlyrainin":0.0,"TIME":"2021-02-22 10:58:00","monthlyrainin":26.162,"dailyrainin":0.0,"solarradiation":279.93,"windgust":0.0,"humidity":73.0,"windspeed":0.0,"id":3584,"maxdailygust":2.19,"weeklyrainin":0.0},{"loc_oid":1,"uv":3,"temp":14.389,"yearlyrainin":41.148,"dewpoint":7.2,"feelslike":14.389,"winddir":304,"hourlyrainin":0.0,"TIME":"2021-02-22 11:08:00","monthlyrainin":26.162,"dailyrainin":0.0,"solarradiation":306.63,"windgust":0.0,"humidity":62.0,"windspeed":0.0,"id":3585,"maxdailygust":2.19,"weeklyrainin":0.0},{"loc_oid":1,"uv":3,"temp":15.778,"yearlyrainin":41.148,"dewpoint":6.489,"feelslike":15.778,"winddir":256,"hourlyrainin":0.0,"TIME":"2021-02-22 11:18:00","monthlyrainin":26.162,"dailyrainin":0.0,"solarradiation":333.51,"windgust":0.0,"humidity":54.0,"windspeed":0.0,"id":3586,"maxdailygust":2.19,"weeklyrainin":0.0},{"loc_oid":1,"uv":3,"temp":17.111,"yearlyrainin":41.148,"dewpoint":6.6,"feelslike":17.111,"winddir":20,"hourlyrainin":0.0,"TIME":"2021-02-22 11:28:00","monthlyrainin":26.162,"dailyrainin":0.0,"solarradiation":355.08,"windgust":1.118,"humidity":50.0,"windspeed":0.0,"id":3587,"maxdailygust":3.308,"weeklyrainin":0.0},{"loc_oid":1,"uv":3,"temp":17.889,"yearlyrainin":41.148,"dewpoint":8.172,"feelslike":17.889,"winddir":249,"hourlyrainin":0.0,"TIME":"2021-02-22 11:38:00","monthlyrainin":26.162,"dailyrainin":0.0,"solarradiation":371.54,"windgust":4.381,"humidity":53.0,"windspeed":3.71,"id":3588,"maxdailygust":4.381,"weeklyrainin":0.0},{"loc_oid":1,"uv":3,"temp":18.222,"yearlyrainin":41.148,"dewpoint":7.911,"feelslike":18.222,"winddir":282,"hourlyrainin":0.0,"TIME":"2021-02-22 11:48:00","monthlyrainin":26.162,"dailyrainin":0.0,"solarradiation":397.65,"windgust":2.19,"humidity":51.0,"windspeed":1.207,"id":3589,"maxdailygust":5.498,"weeklyrainin":0.0},{"loc_oid":1,"uv":3,"temp":18.5,"yearlyrainin":41.148,"dewpoint":8.167,"feelslike":18.5,"winddir":264,"hourlyrainin":0.0,"TIME":"2021-02-22 11:58:00","monthlyrainin":26.162,"dailyrainin":0.0,"solarradiation":423.87,"windgust":3.308,"humidity":51.0,"windspeed":2.682,"id":3590,"maxdailygust":5.498,"weeklyrainin":0.0},{"loc_oid":1,"uv":3,"temp":18.889,"yearlyrainin":41.148,"dewpoint":8.233,"feelslike":18.889,"winddir":250,"hourlyrainin":0.0,"TIME":"2021-02-22 12:09:00","monthlyrainin":26.162,"dailyrainin":0.0,"solarradiation":446.48,"windgust":3.308,"humidity":50.0,"windspeed":2.503,"id":3591,"maxdailygust":5.498,"weeklyrainin":0.0},{"loc_oid":1,"uv":4,"temp":19.278,"yearlyrainin":41.148,"dewpoint":8.589,"feelslike":19.278,"winddir":273,"hourlyrainin":0.0,"TIME":"2021-02-22 12:19:00","monthlyrainin":26.162,"dailyrainin":0.0,"solarradiation":467.66,"windgust":3.308,"humidity":50.0,"windspeed":2.503,"id":3592,"maxdailygust":5.498,"weeklyrainin":0.0},{"loc_oid":1,"uv":4,"temp":19.611,"yearlyrainin":41.148,"dewpoint":8.294,"feelslike":19.611,"winddir":41,"hourlyrainin":0.0,"TIME":"2021-02-22 12:29:00","monthlyrainin":26.162,"dailyrainin":0.0,"solarradiation":481.83,"windgust":1.118,"humidity":48.0,"windspeed":0.0,"id":3593,"maxdailygust":5.498,"weeklyrainin":0.0},{"loc_oid":1,"uv":3,"temp":19.778,"yearlyrainin":41.148,"dewpoint":8.444,"feelslike":19.778,"winddir":243,"hourlyrainin":0.0,"TIME":"2021-02-22 12:39:00","monthlyrainin":26.162,"dailyrainin":0.0,"solarradiation":493.12,"windgust":3.308,"humidity":48.0,"windspeed":2.012,"id":3594,"maxdailygust":5.498,"weeklyrainin":0.0},{"loc_oid":1,"uv":3,"temp":20.111,"yearlyrainin":41.148,"dewpoint":9.056,"feelslike":19.456,"winddir":264,"hourlyrainin":0.0,"TIME":"2021-02-22 12:49:00","monthlyrainin":26.162,"dailyrainin":0.0,"solarradiation":497.74,"windgust":3.308,"humidity":49.0,"windspeed":2.593,"id":3595,"maxdailygust":5.498,"weeklyrainin":0.0},{"loc_oid":1,"uv":3,"temp":20.222,"yearlyrainin":41.148,"dewpoint":8.539,"feelslike":19.528,"winddir":278,"hourlyrainin":0.0,"TIME":"2021-02-22 12:59:00","monthlyrainin":26.162,"dailyrainin":0.0,"solarradiation":501.63,"windgust":1.118,"humidity":47.0,"windspeed":0.179,"id":3596,"maxdailygust":6.705,"weeklyrainin":0.0},{"loc_oid":1,"uv":3,"temp":20.278,"yearlyrainin":41.148,"dewpoint":9.211,"feelslike":19.639,"winddir":251,"hourlyrainin":0.0,"TIME":"2021-02-22 13:09:00","monthlyrainin":26.162,"dailyrainin":0.0,"solarradiation":504.79,"windgust":3.308,"humidity":49.0,"windspeed":2.19,"id":3597,"maxdailygust":7.778,"weeklyrainin":0.0},{"loc_oid":1,"uv":3,"temp":20.222,"yearlyrainin":41.148,"dewpoint":8.85,"feelslike":19.556,"winddir":241,"hourlyrainin":0.0,"TIME":"2021-02-22 13:19:00","monthlyrainin":26.162,"dailyrainin":0.0,"solarradiation":506.66,"windgust":6.705,"humidity":48.0,"windspeed":4.291,"id":3598,"maxdailygust":7.778,"weeklyrainin":0.0},{"loc_oid":1,"uv":3,"temp":20.278,"yearlyrainin":41.148,"dewpoint":8.272,"feelslike":19.561,"winddir":297,"hourlyrainin":0.0,"TIME":"2021-02-22 13:29:00","monthlyrainin":26.162,"dailyrainin":0.0,"solarradiation":503.36,"windgust":3.308,"humidity":46.0,"windspeed":1.609,"id":3599,"maxdailygust":7.778,"weeklyrainin":0.0},{"loc_oid":1,"uv":3,"temp":20.611,"yearlyrainin":41.148,"dewpoint":8.256,"feelslike":19.9,"winddir":326,"hourlyrainin":0.0,"TIME":"2021-02-22 13:39:00","monthlyrainin":26.162,"dailyrainin":0.0,"solarradiation":504.61,"windgust":2.19,"humidity":45.0,"windspeed":1.207,"id":3600,"maxdailygust":7.778,"weeklyrainin":0.0},{"loc_oid":1,"uv":3,"temp":20.722,"yearlyrainin":41.148,"dewpoint":8.994,"feelslike":20.078,"winddir":253,"hourlyrainin":0.0,"TIME":"2021-02-22 13:49:00","monthlyrainin":26.162,"dailyrainin":0.0,"solarradiation":500.06,"windgust":2.19,"humidity":47.0,"windspeed":0.581,"id":3601,"maxdailygust":8.896,"weeklyrainin":0.0},{"loc_oid":1,"uv":3,"temp":20.5,"yearlyrainin":41.148,"dewpoint":9.106,"feelslike":19.861,"winddir":260,"hourlyrainin":0.0,"TIME":"2021-02-22 13:59:00","monthlyrainin":26.162,"dailyrainin":0.0,"solarradiation":499.61,"windgust":2.19,"humidity":48.0,"windspeed":0.179,"id":3602,"maxdailygust":8.896,"weeklyrainin":0.0},{"loc_oid":1,"uv":2,"temp":20.5,"yearlyrainin":41.148,"dewpoint":9.411,"feelslike":19.883,"winddir":342,"hourlyrainin":0.0,"TIME":"2021-02-22 14:09:00","monthlyrainin":26.162,"dailyrainin":0.0,"solarradiation":462.84,"windgust":3.308,"humidity":49.0,"windspeed":1.788,"id":3603,"maxdailygust":8.896,"weeklyrainin":0.0},{"loc_oid":1,"uv":2,"temp":20.5,"yearlyrainin":41.148,"dewpoint":9.711,"feelslike":19.911,"winddir":43,"hourlyrainin":0.0,"TIME":"2021-02-22 14:19:00","monthlyrainin":26.162,"dailyrainin":0.0,"solarradiation":487.56,"windgust":1.118,"humidity":50.0,"windspeed":0.0,"id":3604,"maxdailygust":8.896,"weeklyrainin":0.0},{"loc_oid":1,"uv":2,"temp":20.278,"yearlyrainin":41.148,"dewpoint":9.511,"feelslike":19.667,"winddir":335,"hourlyrainin":0.0,"TIME":"2021-02-22 14:29:00","monthlyrainin":26.162,"dailyrainin":0.0,"solarradiation":484.82,"windgust":5.498,"humidity":50.0,"windspeed":3.397,"id":3605,"maxdailygust":8.896,"weeklyrainin":0.0},{"loc_oid":1,"uv":2,"temp":19.889,"yearlyrainin":41.148,"dewpoint":8.239,"feelslike":19.889,"winddir":262,"hourlyrainin":0.0,"TIME":"2021-02-22 14:39:00","monthlyrainin":26.162,"dailyrainin":0.0,"solarradiation":469.4,"windgust":3.308,"humidity":47.0,"windspeed":1.922,"id":3606,"maxdailygust":8.896,"weeklyrainin":0.0},{"loc_oid":1,"uv":2,"temp":19.778,"yearlyrainin":41.148,"dewpoint":7.167,"feelslike":19.778,"winddir":331,"hourlyrainin":0.0,"TIME":"2021-02-22 14:49:00","monthlyrainin":26.162,"dailyrainin":0.0,"solarradiation":463.18,"windgust":3.308,"humidity":44.0,"windspeed":2.19,"id":3607,"maxdailygust":8.896,"weeklyrainin":0.0},{"loc_oid":1,"uv":2,"temp":19.778,"yearlyrainin":41.148,"dewpoint":7.822,"feelslike":19.778,"winddir":355,"hourlyrainin":0.0,"TIME":"2021-02-22 14:59:00","monthlyrainin":26.162,"dailyrainin":0.0,"solarradiation":445.09,"windgust":3.308,"humidity":46.0,"windspeed":2.012,"id":3608,"maxdailygust":8.896,"weeklyrainin":0.0},{"loc_oid":1,"uv":2,"temp":19.778,"yearlyrainin":41.148,"dewpoint":8.133,"feelslike":19.778,"winddir":309,"hourlyrainin":0.0,"TIME":"2021-02-22 15:09:00","monthlyrainin":26.162,"dailyrainin":0.0,"solarradiation":435.33,"windgust":4.381,"humidity":47.0,"windspeed":2.906,"id":3609,"maxdailygust":8.896,"weeklyrainin":0.0},{"loc_oid":1,"uv":2,"temp":19.5,"yearlyrainin":41.148,"dewpoint":7.883,"feelslike":19.5,"winddir":42,"hourlyrainin":0.0,"TIME":"2021-02-22 15:19:00","monthlyrainin":26.162,"dailyrainin":0.0,"solarradiation":409.56,"windgust":3.308,"humidity":47.0,"windspeed":1.609,"id":3610,"maxdailygust":8.896,"weeklyrainin":0.0},{"loc_oid":1,"uv":2,"temp":19.222,"yearlyrainin":41.148,"dewpoint":6.667,"feelslike":19.222,"winddir":353,"hourlyrainin":0.0,"TIME":"2021-02-22 15:29:00","monthlyrainin":26.162,"dailyrainin":0.0,"solarradiation":408.49,"windgust":6.705,"humidity":44.0,"windspeed":5.409,"id":3611,"maxdailygust":8.896,"weeklyrainin":0.0},{"loc_oid":1,"uv":1,"temp":19.0,"yearlyrainin":41.148,"dewpoint":7.111,"feelslike":19.0,"winddir":330,"hourlyrainin":0.0,"TIME":"2021-02-22 15:39:00","monthlyrainin":26.162,"dailyrainin":0.0,"solarradiation":387.82,"windgust":4.381,"humidity":46.0,"windspeed":2.503,"id":3612,"maxdailygust":8.896,"weeklyrainin":0.0},{"loc_oid":1,"uv":1,"temp":18.778,"yearlyrainin":41.148,"dewpoint":6.911,"feelslike":18.778,"winddir":299,"hourlyrainin":0.0,"TIME":"2021-02-22 15:49:00","monthlyrainin":26.162,"dailyrainin":0.0,"solarradiation":344.76,"windgust":4.381,"humidity":46.0,"windspeed":2.19,"id":3613,"maxdailygust":8.896,"weeklyrainin":0.0},{"loc_oid":1,"uv":1,"temp":18.5,"yearlyrainin":41.148,"dewpoint":6.656,"feelslike":18.5,"winddir":324,"hourlyrainin":0.0,"TIME":"2021-02-22 15:59:00","monthlyrainin":26.162,"dailyrainin":0.0,"solarradiation":327.09,"windgust":6.705,"humidity":46.0,"windspeed":4.291,"id":3614,"maxdailygust":8.896,"weeklyrainin":0.0},{"loc_oid":1,"uv":1,"temp":18.278,"yearlyrainin":41.148,"dewpoint":6.456,"feelslike":18.278,"winddir":341,"hourlyrainin":0.0,"TIME":"2021-02-22 16:09:00","monthlyrainin":26.162,"dailyrainin":0.0,"solarradiation":332.23,"windgust":1.118,"humidity":46.0,"windspeed":0.581,"id":3615,"maxdailygust":8.896,"weeklyrainin":0.0},{"loc_oid":1,"uv":1,"temp":18.111,"yearlyrainin":41.148,"dewpoint":5.661,"feelslike":18.111,"winddir":354,"hourlyrainin":0.0,"TIME":"2021-02-22 16:19:00","monthlyrainin":26.162,"dailyrainin":0.0,"solarradiation":318.02,"windgust":5.498,"humidity":44.0,"windspeed":4.783,"id":3616,"maxdailygust":8.896,"weeklyrainin":0.0},{"loc_oid":1,"uv":1,"temp":17.778,"yearlyrainin":41.148,"dewpoint":5.028,"feelslike":17.778,"winddir":264,"hourlyrainin":0.0,"TIME":"2021-02-22 16:29:00","monthlyrainin":26.162,"dailyrainin":0.0,"solarradiation":306.56,"windgust":1.118,"humidity":43.0,"windspeed":0.581,"id":3617,"maxdailygust":8.896,"weeklyrainin":0.0},{"loc_oid":1,"uv":1,"temp":17.611,"yearlyrainin":41.148,"dewpoint":4.539,"feelslike":17.611,"winddir":342,"hourlyrainin":0.0,"TIME":"2021-02-22 16:39:00","monthlyrainin":26.162,"dailyrainin":0.0,"solarradiation":288.23,"windgust":3.308,"humidity":42.0,"windspeed":1.922,"id":3618,"maxdailygust":8.896,"weeklyrainin":0.0},{"loc_oid":1,"uv":1,"temp":17.222,"yearlyrainin":41.148,"dewpoint":4.528,"feelslike":17.222,"winddir":319,"hourlyrainin":0.0,"TIME":"2021-02-22 16:49:00","monthlyrainin":26.162,"dailyrainin":0.0,"solarradiation":271.9,"windgust":2.19,"humidity":43.0,"windspeed":1.922,"id":3619,"maxdailygust":8.896,"weeklyrainin":0.0},{"loc_oid":1,"uv":1,"temp":16.889,"yearlyrainin":41.148,"dewpoint":4.556,"feelslike":16.889,"winddir":342,"hourlyrainin":0.0,"TIME":"2021-02-22 16:59:00","monthlyrainin":26.162,"dailyrainin":0.0,"solarradiation":237.21,"windgust":2.19,"humidity":44.0,"windspeed":0.894,"id":3620,"maxdailygust":8.896,"weeklyrainin":0.0},{"loc_oid":1,"uv":1,"temp":16.389,"yearlyrainin":41.148,"dewpoint":4.422,"feelslike":16.389,"winddir":265,"hourlyrainin":0.0,"TIME":"2021-02-22 17:09:00","monthlyrainin":26.162,"dailyrainin":0.0,"solarradiation":204.6,"windgust":4.381,"humidity":45.0,"windspeed":2.28,"id":3621,"maxdailygust":8.896,"weeklyrainin":0.0},{"loc_oid":1,"uv":1,"temp":15.778,"yearlyrainin":41.148,"dewpoint":4.489,"feelslike":15.778,"winddir":330,"hourlyrainin":0.0,"TIME":"2021-02-22 17:19:00","monthlyrainin":26.162,"dailyrainin":0.0,"solarradiation":169.73,"windgust":4.381,"humidity":47.0,"windspeed":2.012,"id":3622,"maxdailygust":8.896,"weeklyrainin":0.0},{"loc_oid":1,"uv":1,"temp":15.0,"yearlyrainin":41.148,"dewpoint":4.078,"feelslike":15.0,"winddir":301,"hourlyrainin":0.0,"TIME":"2021-02-22 17:29:00","monthlyrainin":26.162,"dailyrainin":0.0,"solarradiation":134.66,"windgust":3.308,"humidity":48.0,"windspeed":1.788,"id":3623,"maxdailygust":8.896,"weeklyrainin":0.0},{"loc_oid":1,"uv":1,"temp":14.278,"yearlyrainin":41.148,"dewpoint":3.417,"feelslike":14.278,"winddir":291,"hourlyrainin":0.0,"TIME":"2021-02-22 17:39:00","monthlyrainin":26.162,"dailyrainin":0.0,"solarradiation":100.97,"windgust":7.778,"humidity":48.0,"windspeed":4.783,"id":3624,"maxdailygust":8.896,"weeklyrainin":0.0},{"loc_oid":1,"uv":0,"temp":13.722,"yearlyrainin":41.148,"dewpoint":3.2,"feelslike":13.722,"winddir":354,"hourlyrainin":0.0,"TIME":"2021-02-22 17:49:00","monthlyrainin":26.162,"dailyrainin":0.0,"solarradiation":52.81,"windgust":4.381,"humidity":49.0,"windspeed":2.503,"id":3625,"maxdailygust":8.896,"weeklyrainin":0.0},{"loc_oid":1,"uv":0,"temp":13.111,"yearlyrainin":41.148,"dewpoint":2.639,"feelslike":13.111,"winddir":313,"hourlyrainin":0.0,"TIME":"2021-02-22 17:59:00","monthlyrainin":26.162,"dailyrainin":0.0,"solarradiation":31.84,"windgust":5.498,"humidity":49.0,"windspeed":2.995,"id":3626,"maxdailygust":8.896,"weeklyrainin":0.0},{"loc_oid":1,"uv":0,"temp":12.722,"yearlyrainin":41.148,"dewpoint":2.561,"feelslike":12.722,"winddir":0,"hourlyrainin":0.0,"TIME":"2021-02-22 18:09:00","monthlyrainin":26.162,"dailyrainin":0.0,"solarradiation":12.67,"windgust":3.308,"humidity":50.0,"windspeed":2.28,"id":3627,"maxdailygust":8.896,"weeklyrainin":0.0},{"loc_oid":1,"uv":0,"temp":12.278,"yearlyrainin":41.148,"dewpoint":2.433,"feelslike":12.278,"winddir":293,"hourlyrainin":0.0,"TIME":"2021-02-22 18:19:00","monthlyrainin":26.162,"dailyrainin":0.0,"solarradiation":3.22,"windgust":2.19,"humidity":51.0,"windspeed":0.894,"id":3628,"maxdailygust":8.896,"weeklyrainin":0.0},{"loc_oid":1,"uv":0,"temp":11.778,"yearlyrainin":41.148,"dewpoint":2.244,"feelslike":11.778,"winddir":3,"hourlyrainin":0.0,"TIME":"2021-02-22 18:29:00","monthlyrainin":26.162,"dailyrainin":0.0,"solarradiation":0.0,"windgust":3.308,"humidity":52.0,"windspeed":1.788,"id":3629,"maxdailygust":8.896,"weeklyrainin":0.0},{"loc_oid":1,"uv":0,"temp":11.389,"yearlyrainin":41.148,"dewpoint":1.883,"feelslike":11.389,"winddir":243,"hourlyrainin":0.0,"TIME":"2021-02-22 18:39:00","monthlyrainin":26.162,"dailyrainin":0.0,"solarradiation":0.0,"windgust":3.308,"humidity":52.0,"windspeed":1.609,"id":3630,"maxdailygust":8.896,"weeklyrainin":0.0},{"loc_oid":1,"uv":0,"temp":11.0,"yearlyrainin":41.148,"dewpoint":1.522,"feelslike":11.0,"winddir":331,"hourlyrainin":0.0,"TIME":"2021-02-22 18:49:00","monthlyrainin":26.162,"dailyrainin":0.0,"solarradiation":0.0,"windgust":4.381,"humidity":52.0,"windspeed":2.012,"id":3631,"maxdailygust":8.896,"weeklyrainin":0.0},{"loc_oid":1,"uv":0,"temp":10.722,"yearlyrainin":41.148,"dewpoint":0.994,"feelslike":10.722,"winddir":32,"hourlyrainin":0.0,"TIME":"2021-02-22 18:59:00","monthlyrainin":26.162,"dailyrainin":0.0,"solarradiation":0.0,"windgust":4.381,"humidity":51.0,"windspeed":2.012,"id":3632,"maxdailygust":8.896,"weeklyrainin":0.0},{"loc_oid":1,"uv":0,"temp":10.278,"yearlyrainin":41.148,"dewpoint":0.311,"feelslike":10.278,"winddir":308,"hourlyrainin":0.0,"TIME":"2021-02-22 19:09:00","monthlyrainin":26.162,"dailyrainin":0.0,"solarradiation":0.0,"windgust":4.381,"humidity":50.0,"windspeed":2.012,"id":3633,"maxdailygust":8.896,"weeklyrainin":0.0},{"loc_oid":1,"uv":0,"temp":10.0,"yearlyrainin":41.148,"dewpoint":0.056,"feelslike":10.0,"winddir":317,"hourlyrainin":0.0,"TIME":"2021-02-22 19:19:00","monthlyrainin":26.162,"dailyrainin":0.0,"solarradiation":0.0,"windgust":2.19,"humidity":50.0,"windspeed":1.296,"id":3634,"maxdailygust":8.896,"weeklyrainin":0.0},{"loc_oid":1,"uv":0,"temp":9.722,"yearlyrainin":41.148,"dewpoint":0.072,"feelslike":9.05,"winddir":257,"hourlyrainin":0.0,"TIME":"2021-02-22 19:29:00","monthlyrainin":26.162,"dailyrainin":0.0,"solarradiation":0.0,"windgust":4.381,"humidity":51.0,"windspeed":1.788,"id":3635,"maxdailygust":8.896,"weeklyrainin":0.0},{"loc_oid":1,"uv":0,"temp":9.278,"yearlyrainin":41.148,"dewpoint":-0.339,"feelslike":7.65,"winddir":261,"hourlyrainin":0.0,"TIME":"2021-02-22 19:39:00","monthlyrainin":26.162,"dailyrainin":0.0,"solarradiation":0.0,"windgust":7.778,"humidity":51.0,"windspeed":2.995,"id":3636,"maxdailygust":8.896,"weeklyrainin":0.0},{"loc_oid":1,"uv":0,"temp":8.889,"yearlyrainin":41.148,"dewpoint":-0.433,"feelslike":8.889,"winddir":274,"hourlyrainin":0.0,"TIME":"2021-02-22 19:49:00","monthlyrainin":26.162,"dailyrainin":0.0,"solarradiation":0.0,"windgust":1.118,"humidity":52.0,"windspeed":0.089,"id":3637,"maxdailygust":8.896,"weeklyrainin":0.0},{"loc_oid":1,"uv":0,"temp":8.5,"yearlyrainin":41.148,"dewpoint":-0.789,"feelslike":7.822,"winddir":6,"hourlyrainin":0.0,"TIME":"2021-02-22 19:59:00","monthlyrainin":26.162,"dailyrainin":0.0,"solarradiation":0.0,"windgust":2.19,"humidity":52.0,"windspeed":1.609,"id":3638,"maxdailygust":8.896,"weeklyrainin":0.0},{"loc_oid":1,"uv":0,"temp":8.111,"yearlyrainin":41.148,"dewpoint":-1.15,"feelslike":8.111,"winddir":319,"hourlyrainin":0.0,"TIME":"2021-02-22 20:09:00","monthlyrainin":26.162,"dailyrainin":0.0,"solarradiation":0.0,"windgust":1.118,"humidity":52.0,"windspeed":0.179,"id":3639,"maxdailygust":8.896,"weeklyrainin":0.0},{"loc_oid":1,"uv":0,"temp":7.778,"yearlyrainin":41.148,"dewpoint":-1.461,"feelslike":7.089,"winddir":298,"hourlyrainin":0.0,"TIME":"2021-02-22 20:19:00","monthlyrainin":26.162,"dailyrainin":0.0,"solarradiation":0.0,"windgust":2.19,"humidity":52.0,"windspeed":1.52,"id":3640,"maxdailygust":8.896,"weeklyrainin":0.0},{"loc_oid":1,"uv":0,"temp":7.5,"yearlyrainin":41.148,"dewpoint":-1.717,"feelslike":6.039,"winddir":308,"hourlyrainin":0.0,"TIME":"2021-02-22 20:29:00","monthlyrainin":26.162,"dailyrainin":0.0,"solarradiation":0.0,"windgust":4.381,"humidity":52.0,"windspeed":2.28,"id":3641,"maxdailygust":8.896,"weeklyrainin":0.0},{"loc_oid":1,"uv":0,"temp":7.222,"yearlyrainin":41.148,"dewpoint":-1.972,"feelslike":7.222,"winddir":16,"hourlyrainin":0.0,"TIME":"2021-02-22 20:39:00","monthlyrainin":26.162,"dailyrainin":0.0,"solarradiation":0.0,"windgust":2.19,"humidity":52.0,"windspeed":1.118,"id":3642,"maxdailygust":8.896,"weeklyrainin":0.0},{"loc_oid":1,"uv":0,"temp":7.0,"yearlyrainin":41.148,"dewpoint":-1.922,"feelslike":7.0,"winddir":318,"hourlyrainin":0.0,"TIME":"2021-02-22 20:49:00","monthlyrainin":26.162,"dailyrainin":0.0,"solarradiation":0.0,"windgust":2.19,"humidity":53.0,"windspeed":1.118,"id":3643,"maxdailygust":8.896,"weeklyrainin":0.0},{"loc_oid":1,"uv":0,"temp":6.722,"yearlyrainin":41.148,"dewpoint":-2.183,"feelslike":5.889,"winddir":350,"hourlyrainin":0.0,"TIME":"2021-02-22 20:59:00","monthlyrainin":26.162,"dailyrainin":0.0,"solarradiation":0.0,"windgust":3.308,"humidity":53.0,"windspeed":1.52,"id":3644,"maxdailygust":8.896,"weeklyrainin":0.0},{"loc_oid":1,"uv":0,"temp":6.389,"yearlyrainin":41.148,"dewpoint":-2.239,"feelslike":6.389,"winddir":327,"hourlyrainin":0.0,"TIME":"2021-02-22 21:09:00","monthlyrainin":26.162,"dailyrainin":0.0,"solarradiation":0.0,"windgust":2.19,"humidity":54.0,"windspeed":1.207,"id":3645,"maxdailygust":8.896,"weeklyrainin":0.0},{"loc_oid":1,"uv":0,"temp":6.222,"yearlyrainin":41.148,"dewpoint":-2.394,"feelslike":6.222,"winddir":6,"hourlyrainin":0.0,"TIME":"2021-02-22 21:19:00","monthlyrainin":26.162,"dailyrainin":0.0,"solarradiation":0.0,"windgust":2.19,"humidity":54.0,"windspeed":0.581,"id":3646,"maxdailygust":8.896,"weeklyrainin":0.0},{"loc_oid":1,"uv":0,"temp":5.889,"yearlyrainin":41.148,"dewpoint":-2.456,"feelslike":5.889,"winddir":329,"hourlyrainin":0.0,"TIME":"2021-02-22 21:29:00","monthlyrainin":26.162,"dailyrainin":0.0,"solarradiation":0.0,"windgust":2.19,"humidity":55.0,"windspeed":0.894,"id":3647,"maxdailygust":8.896,"weeklyrainin":0.0},{"loc_oid":1,"uv":0,"temp":5.778,"yearlyrainin":41.148,"dewpoint":-2.317,"feelslike":4.7,"winddir":345,"hourlyrainin":0.0,"TIME":"2021-02-22 21:39:00","monthlyrainin":26.162,"dailyrainin":0.0,"solarradiation":0.0,"windgust":3.308,"humidity":56.0,"windspeed":1.609,"id":3648,"maxdailygust":8.896,"weeklyrainin":0.0},{"loc_oid":1,"uv":0,"temp":5.5,"yearlyrainin":41.148,"dewpoint":-2.339,"feelslike":4.383,"winddir":352,"hourlyrainin":0.0,"TIME":"2021-02-22 21:49:00","monthlyrainin":26.162,"dailyrainin":0.0,"solarradiation":0.0,"windgust":3.308,"humidity":57.0,"windspeed":1.609,"id":3649,"maxdailygust":8.896,"weeklyrainin":0.0},{"loc_oid":1,"uv":0,"temp":5.278,"yearlyrainin":41.148,"dewpoint":-2.311,"feelslike":3.678,"winddir":350,"hourlyrainin":0.0,"TIME":"2021-02-22 21:59:00","monthlyrainin":26.162,"dailyrainin":0.0,"solarradiation":0.0,"windgust":3.308,"humidity":58.0,"windspeed":2.012,"id":3650,"maxdailygust":8.896,"weeklyrainin":0.0},{"loc_oid":1,"uv":0,"temp":5.111,"yearlyrainin":41.148,"dewpoint":-2.467,"feelslike":3.028,"winddir":334,"hourlyrainin":0.0,"TIME":"2021-02-22 22:09:00","monthlyrainin":26.162,"dailyrainin":0.0,"solarradiation":0.0,"windgust":4.381,"humidity":58.0,"windspeed":2.503,"id":3651,"maxdailygust":8.896,"weeklyrainin":0.0},{"loc_oid":1,"uv":0,"temp":4.778,"yearlyrainin":41.148,"dewpoint":-2.55,"feelslike":3.556,"winddir":10,"hourlyrainin":0.0,"TIME":"2021-02-22 22:19:00","monthlyrainin":26.162,"dailyrainin":0.0,"solarradiation":0.0,"windgust":3.308,"humidity":59.0,"windspeed":1.609,"id":3652,"maxdailygust":8.896,"weeklyrainin":0.0},{"loc_oid":1,"uv":0,"temp":4.5,"yearlyrainin":41.148,"dewpoint":-2.583,"feelslike":2.772,"winddir":358,"hourlyrainin":0.0,"TIME":"2021-02-22 22:29:00","monthlyrainin":26.162,"dailyrainin":0.0,"solarradiation":0.0,"windgust":3.308,"humidity":60.0,"windspeed":2.012,"id":3653,"maxdailygust":8.896,"weeklyrainin":0.0},{"loc_oid":1,"uv":0,"temp":4.222,"yearlyrainin":41.148,"dewpoint":-2.628,"feelslike":4.222,"winddir":314,"hourlyrainin":0.0,"TIME":"2021-02-22 22:39:00","monthlyrainin":26.162,"dailyrainin":0.0,"solarradiation":0.0,"windgust":2.19,"humidity":61.0,"windspeed":1.118,"id":3654,"maxdailygust":8.896,"weeklyrainin":0.0},{"loc_oid":1,"uv":0,"temp":3.889,"yearlyrainin":41.148,"dewpoint":-2.722,"feelslike":1.428,"winddir":330,"hourlyrainin":0.0,"TIME":"2021-02-22 22:49:00","monthlyrainin":26.162,"dailyrainin":0.0,"solarradiation":0.0,"windgust":4.381,"humidity":62.0,"windspeed":2.682,"id":3655,"maxdailygust":8.896,"weeklyrainin":0.0},{"loc_oid":1,"uv":0,"temp":3.722,"yearlyrainin":41.148,"dewpoint":-2.667,"feelslike":0.472,"winddir":326,"hourlyrainin":0.0,"TIME":"2021-02-22 22:59:00","monthlyrainin":26.162,"dailyrainin":0.0,"solarradiation":0.0,"windgust":5.498,"humidity":63.0,"windspeed":3.71,"id":3656,"maxdailygust":8.896,"weeklyrainin":0.0},{"loc_oid":1,"uv":0,"temp":3.389,"yearlyrainin":41.148,"dewpoint":-2.978,"feelslike":0.911,"winddir":330,"hourlyrainin":0.0,"TIME":"2021-02-22 23:09:00","monthlyrainin":26.162,"dailyrainin":0.0,"solarradiation":0.0,"windgust":3.308,"humidity":63.0,"windspeed":2.593,"id":3657,"maxdailygust":8.896,"weeklyrainin":0.0},{"loc_oid":1,"uv":0,"temp":3.222,"yearlyrainin":41.148,"dewpoint":-3.139,"feelslike":0.711,"winddir":352,"hourlyrainin":0.0,"TIME":"2021-02-22 23:19:00","monthlyrainin":26.162,"dailyrainin":0.0,"solarradiation":0.0,"windgust":3.308,"humidity":63.0,"windspeed":2.593,"id":3658,"maxdailygust":8.896,"weeklyrainin":0.0},{"loc_oid":1,"uv":0,"temp":3.0,"yearlyrainin":41.148,"dewpoint":-3.35,"feelslike":0.444,"winddir":3,"hourlyrainin":0.0,"TIME":"2021-02-22 23:29:00","monthlyrainin":26.162,"dailyrainin":0.0,"solarradiation":0.0,"windgust":4.381,"humidity":63.0,"windspeed":2.593,"id":3659,"maxdailygust":8.896,"weeklyrainin":0.0},{"loc_oid":1,"uv":0,"temp":2.778,"yearlyrainin":41.148,"dewpoint":-3.989,"feelslike":-0.161,"winddir":320,"hourlyrainin":0.0,"TIME":"2021-02-22 23:39:00","monthlyrainin":26.162,"dailyrainin":0.0,"solarradiation":0.0,"windgust":5.498,"humidity":61.0,"windspeed":2.995,"id":3660,"maxdailygust":8.896,"weeklyrainin":0.0},{"loc_oid":1,"uv":0,"temp":2.611,"yearlyrainin":41.148,"dewpoint":-3.717,"feelslike":1.194,"winddir":314,"hourlyrainin":0.0,"TIME":"2021-02-22 23:49:00","monthlyrainin":26.162,"dailyrainin":0.0,"solarradiation":0.0,"windgust":3.308,"humidity":63.0,"windspeed":1.52,"id":3661,"maxdailygust":8.896,"weeklyrainin":0.0},{"loc_oid":1,"uv":0,"temp":2.5,"yearlyrainin":41.148,"dewpoint":-3.822,"feelslike":-0.144,"winddir":310,"hourlyrainin":0.0,"TIME":"2021-02-22 23:59:00","monthlyrainin":26.162,"dailyrainin":0.0,"solarradiation":0.0,"windgust":4.381,"humidity":63.0,"windspeed":2.593,"id":3662,"maxdailygust":8.896,"weeklyrainin":0.0}]}